examples/example_redeem.py
poly_web3/__init__.py
poly_web3/const.py
poly_web3/log.py
poly_web3/schema.py
poly_web3/signature/__init__.py
poly_web3/signature/build.py
poly_web3/signature/hash_message.py
poly_web3/signature/secp256k1.py
poly_web3/web3_service/__init__.py
poly_web3/web3_service/base.py
poly_web3/web3_service/eoa_service.py
poly_web3/web3_service/proxy_service.py
poly_web3/web3_service/safe_service.py
poly_web3-1.0.0.dist-info/METADATA
poly_web3-1.0.0.dist-info/WHEEL
poly_web3-1.0.0.dist-info/top_level.txt
poly_web3-1.0.0.dist-info/RECORD
