Metadata-Version: 2.4
Name: poly-web3
Version: 1.0.0
Summary: Polymarket Proxy wallet redeem SDK - Execute redeem operations on Polymarket using proxy wallets
Home-page: https://github.com/tosmart01/poly-web3
Author: PinBar
Project-URL: Homepage, https://github.com/tosmart01/poly-web3
Project-URL: Repository, https://github.com/tosmart01/poly-web3
Project-URL: Bug Tracker, https://github.com/tosmart01/poly-web3/issues
Keywords: polymarket,web3,proxy,wallet,redeem,blockchain,polygon
Classifier: Development Status :: 3 - Alpha
Classifier: Intended Audience :: Developers
Classifier: License :: OSI Approved :: MIT License
Classifier: Programming Language :: Python :: 3
Classifier: Programming Language :: Python :: 3.11
Classifier: Topic :: Software Development :: Libraries :: Python Modules
Classifier: Topic :: Internet :: WWW/HTTP
Requires-Python: >=3.11
Requires-Dist: py-clob-client>=0.25.0
Requires-Dist: py-builder-relayer-client>=0.0.1
Requires-Dist: web3==6.8
Requires-Dist: eth-utils==5.3.1
Requires-Dist: setuptools>=80.9.0
Dynamic: home-page
Dynamic: requires-python
